invrs_utils/__init__.py
invrs_utils/py.typed
invrs_utils/experiment/__init__.py
invrs_utils/experiment/checkpoint.py
invrs_utils/experiment/data.py
invrs_utils/experiment/experiment.py
invrs_utils/experiment/sweep.py
invrs_utils/experiment/work_unit.py
invrs_utils-1.4.1.dist-info/licenses/LICENSE
invrs_utils-1.4.1.dist-info/METADATA
invrs_utils-1.4.1.dist-info/WHEEL
invrs_utils-1.4.1.dist-info/top_level.txt
invrs_utils-1.4.1.dist-info/RECORD
