Metadata-Version: 2.4
Name: invrs_utils
Version: 1.4.1
Summary: Miscellaneous utilities for the invrs-io ecosystem
Author-email: "Martin F. Schubert" <mfschubert@gmail.com>
Maintainer-email: "Martin F. Schubert" <mfschubert@gmail.com>
License-Expression: MIT
Keywords: topology,optimization,jax,inverse design
Requires-Python: >=3.7
License-File: LICENSE
Requires-Dist: jax>=0.4.36
Requires-Dist: pandas
Requires-Dist: totypes
Requires-Dist: tqdm
Requires-Dist: types-tqdm
Provides-Extra: tests
Requires-Dist: parameterized; extra == "tests"
Requires-Dist: pytest; extra == "tests"
Requires-Dist: pytest-cov; extra == "tests"
Requires-Dist: pytest-subtests; extra == "tests"
Requires-Dist: invrs-gym; extra == "tests"
Requires-Dist: invrs-opt; extra == "tests"
Provides-Extra: dev
Requires-Dist: bump-my-version; extra == "dev"
Requires-Dist: darglint; extra == "dev"
Requires-Dist: invrs_utils[tests]; extra == "dev"
Requires-Dist: mypy; extra == "dev"
Requires-Dist: pandas-stubs; extra == "dev"
Requires-Dist: pre-commit; extra == "dev"
Dynamic: license-file
